README.rst
setup.py
chdlab/Telnet_DUT.py
chdlab/WISP.py
chdlab/__init__.py
chdlab/chdlab.py
chdlab/chdlab_ConfParsXLS.py
chdlab/chdlab_GW.py
chdlab/chdlab_buildbot.py
chdlab/chdlab_file_handler.py
chdlab/chdlab_flash.py
chdlab/chdlab_jira.py
chdlab/chdlab_print.py
chdlab/chdlab_telnet.py
chdlab/chdlab_tftp.py
chdlab/chdlab_traffic_run.py
chdlab/chdlab_wisp.py
chdlab/test.py
chdlab_tools.egg-info/PKG-INFO
chdlab_tools.egg-info/SOURCES.txt
chdlab_tools.egg-info/dependency_links.txt
chdlab_tools.egg-info/top_level.txt
lab_management/__init__.py
lab_management/chdlab_jira_allocation.py
performance/__init__.py
performance/chdlab_convert.py
performance/chdlab_endpoint.py
performance/chdlab_iperf_cmd.py
performance/chdlab_stream.py
performance/chdlab_traffic_run.py