Metadata-Version: 1.0
Name: chdlab-tools
Version: 1.2.0
Summary: QA_Unit-Tests
Home-page: UNKNOWN
Author: Koby_Gueta
Author-email: koby.gueta@intel.com
License: UNKNOWN
Platform: UNKNOWN
